besnappy/__init__.py
besnappy/tickets.py
besnappy/tests/__init__.py
besnappy/tests/test_tickets.py
besnappy-0.1.0.dist-info/DESCRIPTION.rst
besnappy-0.1.0.dist-info/METADATA
besnappy-0.1.0.dist-info/metadata.json
besnappy-0.1.0.dist-info/RECORD
besnappy-0.1.0.dist-info/top_level.txt
besnappy-0.1.0.dist-info/WHEEL
