Metadata-Version: 2.0
Name: besnappy
Version: 0.1.0
Summary: An unofficial client library for the BeSnappy HTTP API.
Home-page: http://github.com/westerncapelabs/besnappy
Author: Western Cap Labs
Author-email: devops@westerncapelabs.com
License: BSD
Platform: UNKNOWN
Classifier: Development Status :: 4 - Beta
Classifier: Intended Audience :: Developers
Classifier: License :: OSI Approved :: BSD License
Classifier: Operating System :: POSIX
Classifier: Programming Language :: Python
Classifier: Topic :: Software Development :: Libraries :: Python Modules
Classifier: Topic :: System :: Networking
Requires-Dist: requests (>=2)
